nb_unittest/__init__.py
nb_unittest/analysis.py
nb_unittest/tagcache.py
nb_unittest/templ.py
nb_unittest/transforms.py
nb_unittest/unit.py
nb_unittest/templates/assertion.html
nb_unittest/templates/missing.html
nb_unittest/templates/result.html
nb_unittest/templates/wait.html
nb_unittest-1.0.2.dist-info/licenses/LICENSE
nb_unittest-1.0.2.dist-info/METADATA
nb_unittest-1.0.2.dist-info/WHEEL
nb_unittest-1.0.2.dist-info/top_level.txt
nb_unittest-1.0.2.dist-info/RECORD
